luxerone/__init__.py
luxerone/api.py
luxerone/client.py
luxerone/exceptions.py
luxerone/forms.py
luxerone/package.py
luxerone/user.py
luxerone-0.1.dist-info/LICENSE
luxerone-0.1.dist-info/METADATA
luxerone-0.1.dist-info/WHEEL
luxerone-0.1.dist-info/top_level.txt
luxerone-0.1.dist-info/RECORD
