Metadata-Version: 2.1
Name: luxerone
Version: 0.1
Summary: Unofficial LuxerOne residential API client for Python.
Author-email: Patrick Shinn <shinn5112@gmail.com>
Project-URL: Homepage, https://github.com/shinn5112/luxerone
Project-URL: Bug Tracker, https://github.com/shinn5112/luxerone/issues
Project-URL: Documentation, https://luxerone.readthedocs.io/en/latest/
Classifier: Programming Language :: Python :: 3
Classifier: License :: OSI Approved :: MIT License
Classifier: Operating System :: OS Independent
Requires-Python: >=3.7
License-File: LICENSE
